MANIFEST.in
README.rst
setup.cfg
setup.py
docs/HISTORY.txt
zopeskel/.DS_Store
zopeskel/__init__.py
zopeskel.diazochildtheme.egg-info/PKG-INFO
zopeskel.diazochildtheme.egg-info/SOURCES.txt
zopeskel.diazochildtheme.egg-info/dependency_links.txt
zopeskel.diazochildtheme.egg-info/entry_points.txt
zopeskel.diazochildtheme.egg-info/namespace_packages.txt
zopeskel.diazochildtheme.egg-info/not-zip-safe
zopeskel.diazochildtheme.egg-info/requires.txt
zopeskel.diazochildtheme.egg-info/top_level.txt
zopeskel/diazochildtheme/.DS_Store
zopeskel/diazochildtheme/TODO.txt
zopeskel/diazochildtheme/__init__.py
zopeskel/diazochildtheme/diazochildtheme.py
zopeskel/diazochildtheme/templates/.DS_Store
zopeskel/diazochildtheme/templates/diazochildtheme/.DS_Store
zopeskel/diazochildtheme/templates/diazochildtheme/bootstrap.py
zopeskel/diazochildtheme/templates/diazochildtheme/buildout.cfg_tmpl
zopeskel/diazochildtheme/templates/diazochildtheme/plone.cfg
zopeskel/diazochildtheme/templates/diazochildtheme/setup.cfg
zopeskel/diazochildtheme/templates/diazochildtheme/setup.py_tmpl
zopeskel/diazochildtheme/templates/diazochildtheme/+namespace_package+/.DS_Store
zopeskel/diazochildtheme/templates/diazochildtheme/+namespace_package+/+package+/.DS_Store
zopeskel/diazochildtheme/templates/diazochildtheme/+namespace_package+/+package+/configure.zcml_tmpl
zopeskel/diazochildtheme/templates/diazochildtheme/+namespace_package+/+package+/interfaces.py
zopeskel/diazochildtheme/templates/diazochildtheme/+namespace_package+/+package+/version.txt_tmpl
zopeskel/diazochildtheme/templates/diazochildtheme/+namespace_package+/+package+/diazo_resources/.DS_Store
zopeskel/diazochildtheme/templates/diazochildtheme/+namespace_package+/+package+/diazo_resources/README.txt_tmpl
zopeskel/diazochildtheme/templates/diazochildtheme/+namespace_package+/+package+/diazo_resources/favicon.ico
zopeskel/diazochildtheme/templates/diazochildtheme/+namespace_package+/+package+/diazo_resources/index.html_tmpl
zopeskel/diazochildtheme/templates/diazochildtheme/+namespace_package+/+package+/diazo_resources/manifest.cfg_tmpl
zopeskel/diazochildtheme/templates/diazochildtheme/+namespace_package+/+package+/diazo_resources/preview.png
zopeskel/diazochildtheme/templates/diazochildtheme/+namespace_package+/+package+/diazo_resources/rules.xml
