Metadata-Version: 1.1
Name: zopeskel.diazochildtheme
Version: 0.1
Summary: Paster templates for Plone diazotheme.frameworks bootstrap childtheme package
Home-page: http://github.com/espenmn/zopeskel.diazochildtheme
Author: Espen Moe-Nilssen
Author-email: espen@medialog.no
License: GPL 2
Keywords: plone zope diazo bootstrap medialog
Platform: UNKNOWN
Classifier: Programming Language :: Python
Classifier: Framework :: Plone
Classifier: Framework :: Zope3
Classifier: Topic :: Software Development :: Libraries :: Python Modules
